LICENCE.txt
MANIFEST.in
README.md
setup.py
lifelib/.git
lifelib/.gitignore
lifelib/.gitlab-ci.yml
lifelib/.gitmodules
lifelib/LICENCE.txt
lifelib/README.md
lifelib/__init__.py
lifelib/_version.py
lifelib/autocompile.py
lifelib/bitbounds.h
lifelib/bitworld.h
lifelib/classifier.h
lifelib/cygbash.sh
lifelib/dd0e0p.cpp
lifelib/dsds.h
lifelib/incubator.h
lifelib/lifelib.cpp
lifelib/lifetree.h
lifelib/lifetree_abstract.h
lifelib/pattern2.h
lifelib/sanirule.h
lifelib/spantree.h
lifelib/sparked.mc
lifelib/ssplit.h
lifelib/streamlife.h
lifelib/test_spantree.cpp
lifelib/upattern.cpp
lifelib/upattern.h
lifelib/avxlife/boolean.out
lifelib/avxlife/bytediff_avx.asm
lifelib/avxlife/bytediff_sse2.asm
lifelib/avxlife/cumsum_avx.asm
lifelib/avxlife/cumsum_sse2.asm
lifelib/avxlife/directions.h
lifelib/avxlife/eightbit.h
lifelib/avxlife/eightbit_sse2.asm
lifelib/avxlife/eors.h
lifelib/avxlife/hadd_avx.asm
lifelib/avxlife/hadd_avx2.asm
lifelib/avxlife/hadd_sse2.asm
lifelib/avxlife/isoluts.h
lifelib/avxlife/ladd_avx.asm
lifelib/avxlife/ladd_avx2.asm
lifelib/avxlife/ladd_sse2.asm
lifelib/avxlife/leaf_iterators.h
lifelib/avxlife/leaf_iterators_avx512.h
lifelib/avxlife/lifeconsts.h
lifelib/avxlife/lifeperm.h
lifelib/avxlife/ltl.h
lifelib/avxlife/test8bit.cpp
lifelib/avxlife/uli.h
lifelib/avxlife/lifelogic/iterators_all.h
lifelib/avxlife/lifelogic/iterators_b3s23.h
lifelib/avxlife/lifelogic/iterators_gpu.h
lifelib/cgold/__init__.py
lifelib/cgold/block0.cbc
lifelib/cgold/describe.py
lifelib/cgold/difficulties.h
lifelib/cgold/difficulties.inc
lifelib/cgold/lcdupd.sh
lifelib/classic/jumptable.h
lifelib/classic/jumptable.py
lifelib/classic/switchtable.h
lifelib/classic/switchtable.py
lifelib/classic/utile.h
lifelib/classic/vtile.h
lifelib/classic/vtile28.h
lifelib/classic/vtile44.h
lifelib/cpads/.git
lifelib/cpads/LICENCE.txt
lifelib/cpads/README.md
lifelib/cpads/include/cpads/core.hpp
lifelib/cpads/include/cpads/indextable.hpp
lifelib/cpads/include/cpads/ivector.hpp
python_lifelib.egg-info/PKG-INFO
python_lifelib.egg-info/SOURCES.txt
python_lifelib.egg-info/dependency_links.txt
python_lifelib.egg-info/not-zip-safe
python_lifelib.egg-info/requires.txt
python_lifelib.egg-info/top_level.txt