Metadata-Version: 2.1
Name: python-lifelib
Version: 2.5.6
Summary: Algorithms for manipulating and simulating patterns in cellular automata
Home-page: https://gitlab.com/apgoucher/lifelib
Author: Adam P. Goucher
Author-email: adam@hatsya.com
License: MIT
Platform: UNKNOWN
Classifier: Development Status :: 4 - Beta
Classifier: License :: OSI Approved :: MIT License
Classifier: Operating System :: POSIX
Classifier: Programming Language :: C++
Classifier: Programming Language :: Assembly
Classifier: Programming Language :: Python :: 2
Classifier: Programming Language :: Python :: 2.7
Classifier: Programming Language :: Python :: 3
Classifier: Programming Language :: Python :: 3.5
Classifier: Programming Language :: Python :: 3.6
Classifier: Programming Language :: Python :: 3.7
Classifier: Programming Language :: Python :: 3.8
Classifier: Intended Audience :: Science/Research
Classifier: Topic :: Scientific/Engineering :: Artificial Life
Classifier: Topic :: Scientific/Engineering :: Mathematics
Provides-Extra: notebook
